src/__init__.py
src/constants.py
src/function_deployer.py
src/master_config.py
src/model_asset_hierarchy.py
src/post_commit.py
src/pre_commit.py
src/run.py
src/model/__init__.py
src/model/config.py
src/model/deployment.py
src/model/project.py
src/model/schedule.py
src/model/schedule_assets.py
src/model/scheduling.py
src/schemas/config-schema.yaml
src/util/__init__.py
src/util/cdf.py
src/util/convert_string_times.py
src/util/cron.py
src/util/env.py
src/util/file.py
src/util/functions.py
src/util/github.py
src/util/yaml.py
aruntestpackageair-0.0.3.3.dist-info/METADATA
aruntestpackageair-0.0.3.3.dist-info/WHEEL
aruntestpackageair-0.0.3.3.dist-info/top_level.txt
aruntestpackageair-0.0.3.3.dist-info/RECORD
