Metadata-Version: 2.1
Name: aruntestpackageair
Version: 0.0.3.3
Summary: A small example package to test backend functionality
Home-page: https://github.com/mcarun123/air_backend_test
Author: Zana
Author-email: aarunkaashyap@gmail.com
License: UNKNOWN
Platform: UNKNOWN
Classifier: Programming Language :: Python :: 3
Classifier: License :: OSI Approved :: MIT License
Classifier: Operating System :: OS Independent
Requires-Python: >=3.6
